{"students":[
{"name":"dinesh","rollno":"001","address":"No1,XY Street, Vellore, Tamil Nadu","semester1_name":"Sem2","semester1_sub1":"OOAD","semester1_sub2":"Network Security","semester1_sub3":"Internet of Things","semester2_name":"Sem2","semester2_sub1":"Advanced Data Structure","semester2_sub2":"Programming in java","semester2_sub3":"Web Programming","semester3_name":"Sem3","sub1":"Data Mining","sub2":"Mobile Computing","sub3":"Resource Management Technique","sem1_sub1_mark":"75","sem1_sub2_mark":"80","sem1_sub3_mark":"79","sem1_tot":"234","sem1_grade":"pass","sem2_sub1_mark":"82","sem2_sub2_mark":"83","sem2_sub3_mark":"69","sem2_tot":"234","sem2_grade":"pass","sem3_sub1_mark":"72","sem3_sub2_mark":"80","sem3_sub3_mark":"89","sem3_tot":"241","sem3_grade":"pass"},
{"name":"prem","rollno":"002","address":"No10,YZ Street, Vellore, Tamil Nadu","semester1_name":"Sem2","semester1_sub1":"OOAD","semester1_sub2":"Network Security","semester1_sub3":"Internet of Things","semester2_name":"Sem2","semester2_sub1":"Advanced Data Structure","semester2_sub2":"Programming in java","semester2_sub3":"Web Programming","semester3_name":"Sem3","sub1":"Data Mining","sub2":"Mobile Computing","sub3":"Resource Management Technique","sem1_sub1_mark":"80","sem1_sub2_mark":"75","sem1_sub3_mark":"79","sem1_tot":"234","sem1_grade":"pass","sem2_sub1_mark":"82","sem2_sub2_mark":"85","sem2_sub3_mark":"79","sem2_tot":"246","sem2_grade":"pass","sem3_sub1_mark":"63","sem3_sub2_mark":"71","sem3_sub3_mark":"80","sem3_tot":"214","sem3_grade":"pass"},
{"name":"sandeep","rollno":"003","address":"No20,xYZ Street, Vellore, Tamil Nadu","semester1_name":"Sem2","semester1_sub1":"OOAD","semester1_sub2":"Network Security","semester1_sub3":"Internet of Things","semester2_name":"Sem2","semester2_sub1":"Advanced Data Structure","semester2_sub2":"Programming in java","semester2_sub3":"Web Programming","semester3_name":"Sem3","sub1":"Data Mining","sub2":"Mobile Computing","sub3":"Resource Management Technique","sem1_sub1_mark":"75","sem1_sub2_mark":"82","sem1_sub3_mark":"69","sem1_tot":"226","sem1_grade":"pass","sem2_sub1_mark":"75","sem2_sub2_mark":"65","sem2_sub3_mark":"80","sem2_tot":"220","sem2_grade":"pass","sem3_sub1_mark":"75","sem3_sub2_mark":"71","sem3_sub3_mark":"80","sem3_tot":"226","sem3_grade":"pass"}
]}